libcnml/__init__.py
libcnml/cnml.dtd
libcnml/libcnml.py
libcnml/version.py
libcnml/tests/__init__.py
libcnml/tests/test_libcnml.py
libcnml/tests/data/2525.cnml
libcnml/tests/data/54284.cnml
libcnml/tests/data/54284_invalid.cnml
libcnml/tests/data/55284.cnml
libcnml/tests/data/56604_node.cnml
libcnml/tests/data/empty.cnml
libcnml-0.9.5.dist-info/DESCRIPTION.rst
libcnml-0.9.5.dist-info/METADATA
libcnml-0.9.5.dist-info/RECORD
libcnml-0.9.5.dist-info/WHEEL
libcnml-0.9.5.dist-info/metadata.json
libcnml-0.9.5.dist-info/top_level.txt
