Metadata-Version: 1.1
Name: libcnml
Version: 0.9.5
Summary: A CNML parser for Python
Home-page: https://github.com/PabloCastellano/libcnml/
Author: Pablo Castellano
Author-email: pablo@anche.no
License: GPLv3+
Download-URL: https://github.com/PabloCastellano/libcnml/archive/master.zip
Keywords: cnml,free networks,guifi.net
Platform: UNKNOWN
